PIconnect/AFSDK.py
PIconnect/PI.py
PIconnect/PIAF.py
PIconnect/PIAFAttribute.py
PIconnect/PIAFBase.py
PIconnect/PIConsts.py
PIconnect/PIData.py
PIconnect/PIPoint.py
PIconnect/__init__.py
PIconnect/_time.py
PIconnect/_utils.py
PIconnect/_version.py
PIconnect/config.py
PIconnect/_typing/AF.py
PIconnect/_typing/Asset.py
PIconnect/_typing/Data.py
PIconnect/_typing/EventFrame.py
PIconnect/_typing/Generic.py
PIconnect/_typing/PI.py
PIconnect/_typing/Time.py
PIconnect/_typing/UnitsOfMeasure.py
PIconnect/_typing/__init__.py
PIconnect/_typing/_values.py
PIconnect/_typing/dotnet/Data.py
PIconnect/_typing/dotnet/Net.py
PIconnect/_typing/dotnet/Security.py
PIconnect/_typing/dotnet/__init__.py
piconnect-0.12.4.dist-info/licenses/AUTHORS.rst
piconnect-0.12.4.dist-info/licenses/LICENSE
piconnect-0.12.4.dist-info/METADATA
piconnect-0.12.4.dist-info/WHEEL
piconnect-0.12.4.dist-info/top_level.txt
piconnect-0.12.4.dist-info/RECORD
