Metadata-Version: 2.4
Name: PIconnect
Version: 0.12.4
Summary: PIconnect - Connector to the OSISoft PI and PI-AF databases.
Author-email: Hugo Lapre <dev@tbdwebdesign.nl>
License: MIT
Project-URL: Homepage, https://github.com/Hugovdberg/PIconnect
Project-URL: Repository, https://github.com/Hugovdberg/PIconnect.git
Project-URL: Issues, https://github.com/Hugovdberg/PIconnect/issues
Project-URL: Documentation, https://piconnect.readthedocs.io/en/stable/
Keywords: OSIsoft,AVEVA,PI,Process Information,PIconnect
Classifier: Development Status :: 4 - Beta
Classifier: Intended Audience :: Developers
Classifier: Topic :: Database
Classifier: Programming Language :: Python
Classifier: Programming Language :: Python :: 3
Classifier: Programming Language :: Python :: 3 :: Only
Classifier: Programming Language :: Python :: 3.10
Classifier: Programming Language :: Python :: 3.11
Classifier: Programming Language :: Python :: 3.12
Classifier: Programming Language :: Python :: 3.13
Requires-Python: >=3.11
License-File: LICENSE
License-File: AUTHORS.rst
Requires-Dist: pandas<3,>=2
Requires-Dist: numpy<3,>=2
Requires-Dist: pythonnet>=3
Requires-Dist: wrapt<2,>=1.17
Dynamic: license-file
